cephalon/__init__.py
cephalon/admin.py
cephalon/apps.py
cephalon/migrations/0001_initial.py
cephalon/migrations/__init__.py
cephalon/models.py
cephalon/tests.py
cephalon/views.py
corpus_cephalon-0.1.0.dist-info/METADATA
corpus_cephalon-0.1.0.dist-info/WHEEL
corpus_cephalon-0.1.0.dist-info/RECORD
