Metadata-Version: 2.1
Name: corpus-cephalon
Version: 0.1.0
Summary: User management models and auxilaries for Corpus
Author: Toan Phung
Author-email: toan.phung@proteo.info
Requires-Python: >=3.9,<4.0
Classifier: Programming Language :: Python :: 3
Classifier: Programming Language :: Python :: 3.9
Classifier: Programming Language :: Python :: 3.10
Classifier: Programming Language :: Python :: 3.11
Requires-Dist: django (>=4.2.6,<5.0.0)
